main/__init__.py
my_tgcf/__init__.py
my_tgcf/proxy_parse_tuple.py
tgcf/__init__.py
tgcf/bot/__init__.py
tgcf/bot/live_bot.py
tgcf/bot/utils.py
tgcf/cli.py
tgcf/config.py
tgcf/const.py
tgcf/live.py
tgcf/past.py
tgcf/plugin_models.py
tgcf/plugins/__init__.py
tgcf/plugins/caption.py
tgcf/plugins/filter.py
tgcf/plugins/fmt.py
tgcf/plugins/mark.py
tgcf/plugins/ocr.py
tgcf/plugins/replace.py
tgcf/storage.py
tgcf/utils.py
web_ui/0_👋_Hello.py
web_ui/__init__.py
web_ui/pages/1_🔑_Telegram_Login.py
web_ui/pages/2_⭐_Admins.py
web_ui/pages/3_🔗_Connections.py
web_ui/pages/4_🔌_Plugins.py
web_ui/pages/5_🏃_Run.py
web_ui/pages/6_🔬_Advanced.py
web_ui/password.py
web_ui/run.py
web_ui/utils.py
my_tgcf-0.0.3.dist-info/entry_points.txt
my_tgcf-0.0.3.dist-info/METADATA
my_tgcf-0.0.3.dist-info/WHEEL
my_tgcf-0.0.3.dist-info/RECORD
